libsodium.a
libsodium.la
operations/__init__.py
operations/secure_random/__init__.py
operations/secure_random/test_secure_random.py
pkgconfig/libsodium.pc
tf_encrypted/__init__.py
tf_encrypted/config.py
tf_encrypted/performance.py
tf_encrypted/utils.py
tf_encrypted/convert/__init__.py
tf_encrypted/convert/convert.py
tf_encrypted/convert/nodes.py
tf_encrypted/convert/nodes_test.py
tf_encrypted/keras/__init__.py
tf_encrypted/keras/activations.py
tf_encrypted/keras/losses.py
tf_encrypted/keras/losses_test.py
tf_encrypted/keras/optimizers.py
tf_encrypted/keras/testing_utils.py
tf_encrypted/keras/datasets/__init__.py
tf_encrypted/keras/datasets/convert.py
tf_encrypted/keras/datasets/logistic_artificial.py
tf_encrypted/keras/datasets/mnist.py
tf_encrypted/keras/engine/__init__.py
tf_encrypted/keras/engine/base_layer.py
tf_encrypted/keras/engine/base_layer_utils.py
tf_encrypted/keras/engine/input_layer.py
tf_encrypted/keras/engine/input_layer_test.py
tf_encrypted/keras/layers/__init__.py
tf_encrypted/keras/layers/activation.py
tf_encrypted/keras/layers/activation_test.py
tf_encrypted/keras/layers/convolutional.py
tf_encrypted/keras/layers/convolutional_test.py
tf_encrypted/keras/layers/dense.py
tf_encrypted/keras/layers/dense_test.py
tf_encrypted/keras/layers/flatten.py
tf_encrypted/keras/layers/flatten_test.py
tf_encrypted/keras/layers/layers_utils.py
tf_encrypted/keras/layers/normalization.py
tf_encrypted/keras/layers/normalization_test.py
tf_encrypted/keras/layers/pooling.py
tf_encrypted/keras/layers/pooling_test.py
tf_encrypted/keras/layers/relu.py
tf_encrypted/keras/layers/relu_test.py
tf_encrypted/keras/layers/reshape.py
tf_encrypted/keras/layers/reshape_test.py
tf_encrypted/keras/models/__init__.py
tf_encrypted/keras/models/base_model.py
tf_encrypted/keras/models/sequential.py
tf_encrypted/keras/models/sequential_test.py
tf_encrypted/operations/__init__.py
tf_encrypted/operations/aux/__init__.py
tf_encrypted/operations/aux/aux.py
tf_encrypted-0.9.1.dist-info/LICENSE
tf_encrypted-0.9.1.dist-info/METADATA
tf_encrypted-0.9.1.dist-info/NOTICE
tf_encrypted-0.9.1.dist-info/WHEEL
tf_encrypted-0.9.1.dist-info/top_level.txt
tf_encrypted-0.9.1.dist-info/RECORD
