Metadata-Version: 2.1
Name: tf-encrypted
Version: 0.9.1
Summary: A Framework for Machine Learning on Encrypted Data.
Home-page: https://github.com/tf-encrypted/tf-encrypted
Author: The TF Encrypted Authors
Author-email: contact@tf-encrypted.io
License: Apache License 2.0
Classifier: Programming Language :: Python :: 3
Classifier: License :: OSI Approved :: Apache Software License
Classifier: Development Status :: 2 - Pre-Alpha
Classifier: Operating System :: OS Independent
Classifier: Topic :: Scientific/Engineering :: Artificial Intelligence
Classifier: Topic :: Security :: Cryptography
Requires-Python: >=3.8
License-File: LICENSE
License-File: NOTICE
Requires-Dist: tensorflow (>=2.9.1)
Requires-Dist: numpy (>=1.22.4)
Requires-Dist: pyyaml (>=6.0)
Requires-Dist: tf2onnx (>=1.12.0)
Provides-Extra: tf
Requires-Dist: tensorflow (>=2.9.1) ; extra == 'tf'
